sipmessage/__init__.py
sipmessage/address.py
sipmessage/auth.py
sipmessage/cseq.py
sipmessage/grammar.py
sipmessage/message.py
sipmessage/parameters.py
sipmessage/py.typed
sipmessage/uri.py
sipmessage/utils.py
sipmessage/via.py
sipmessage-0.6.4.dist-info/licenses/LICENSE
sipmessage-0.6.4.dist-info/METADATA
sipmessage-0.6.4.dist-info/WHEEL
sipmessage-0.6.4.dist-info/top_level.txt
sipmessage-0.6.4.dist-info/RECORD
