Metadata-Version: 2.4
Name: sipmessage
Version: 0.6.4
Summary: Pure python parsing of SIP messages and headers
Author-email: Spacinov Engineering <opensource@spacinov.com>
License-Expression: BSD-2-Clause
Project-URL: Documentation, https://sipmessage.readthedocs.io/
Project-URL: Repository, https://github.com/spacinov/sipmessage
Project-URL: Issues, https://github.com/spacinov/sipmessage/issues
Keywords: SIP,RFC3261
Classifier: Development Status :: 4 - Beta
Classifier: Intended Audience :: Developers
Classifier: Intended Audience :: System Administrators
Classifier: Intended Audience :: Telecommunications Industry
Classifier: Operating System :: OS Independent
Classifier: Programming Language :: Python :: 3.10
Classifier: Programming Language :: Python :: 3.11
Classifier: Programming Language :: Python :: 3.12
Classifier: Programming Language :: Python :: 3.13
Classifier: Topic :: Communications :: Telephony
Classifier: Typing :: Typed
Requires-Python: >=3.10
License-File: LICENSE
Provides-Extra: dev
Requires-Dist: check-manifest; extra == "dev"
Requires-Dist: coverage; extra == "dev"
Requires-Dist: mypy; extra == "dev"
Requires-Dist: pyroma; extra == "dev"
Requires-Dist: ruff; extra == "dev"
Dynamic: license-file
